modelprep/__init__.py
modelprep/_version.py
modelprep/cli.py
modelprep/core.py
modelprep-0.2.7.dist-info/METADATA
modelprep-0.2.7.dist-info/WHEEL
modelprep-0.2.7.dist-info/entry_points.txt
modelprep-0.2.7.dist-info/top_level.txt
modelprep-0.2.7.dist-info/RECORD
