Metadata-Version: 2.1
Name: modelprep
Version: 0.2.7
Summary: A CLI tool for managing and analyzing image datasets for model training
Author-email: Harsh Murari <hmurari@visionify.ai>
License: MIT
Project-URL: Homepage, https://github.com/visionify/modelprep
Classifier: Programming Language :: Python :: 3
Classifier: Programming Language :: Python :: 3.8
Classifier: Programming Language :: Python :: 3.9
Classifier: Programming Language :: Python :: 3.10
Classifier: Programming Language :: Python :: 3.11
Classifier: License :: OSI Approved :: MIT License
Classifier: Operating System :: OS Independent
Requires-Python: >=3.7
Requires-Dist: typer >=0.9.0
Requires-Dist: pillow >=10.0.0
Requires-Dist: rich >=13.0.0
Requires-Dist: ultralytics >=8.0.0
Requires-Dist: numpy >=1.22.0
Requires-Dist: roboflow >=1.1.3
Requires-Dist: python-dotenv >=0.19.0
Requires-Dist: psutil >=5.8.0
Provides-Extra: test
Requires-Dist: pytest >=7.0.0 ; extra == 'test'
Requires-Dist: pytest-cov >=4.0.0 ; extra == 'test'
